EvenOrOdd/EvenOrOdd.py
EvenOrOdd/__init__.py
EvenOrOdd/isEven.py
EvenOrOdd-0.1.11.dist-info/METADATA
EvenOrOdd-0.1.11.dist-info/WHEEL
EvenOrOdd-0.1.11.dist-info/top_level.txt
EvenOrOdd-0.1.11.dist-info/RECORD
