Metadata-Version: 2.1
Name: EvenOrOdd
Version: 0.1.11
Summary: What do you think it does
Home-page: UNKNOWN
Author: Sex
License: UNKNOWN
Platform: UNKNOWN
